rofi_tpb/__init__.py
rofi_tpb/cli.py
rofi_tpb/config.py
rofi_tpb/proxy.py
rofi_tpb/settings.py
rofi_tpb/tpb.py
rofi_tpb/utils.py
rofi_tpb-0.2.7.dist-info/entry_points.txt
rofi_tpb-0.2.7.dist-info/LICENSE
rofi_tpb-0.2.7.dist-info/WHEEL
rofi_tpb-0.2.7.dist-info/METADATA
rofi_tpb-0.2.7.dist-info/RECORD
