Metadata-Version: 2.1
Name: rofi-tpb
Version: 0.2.7
Summary: Dynamic menu interface for TPB, built with rofi in mind.
Home-page: https://github.com/loiccoyle/rofi-tpb
License: MIT
Keywords: thepiratebay,tpb,rofi,dmenu
Author: Loic Coyle
Author-email: loic.coyle@hotmail.fr
Requires-Python: >=3.6.2,<4.0.0
Classifier: License :: OSI Approved :: MIT License
Classifier: Operating System :: MacOS
Classifier: Operating System :: Microsoft :: Windows
Classifier: Operating System :: Unix
Classifier: Programming Language :: Python
Classifier: Programming Language :: Python :: 3
Classifier: Programming Language :: Python :: 3.7
Classifier: Programming Language :: Python :: 3.8
Classifier: Programming Language :: Python :: 3.9
Classifier: Topic :: Utilities
Requires-Dist: dynmen (>=0.1.5,<0.2.0)
Requires-Dist: lxml (>=4.6.1,<5.0.0)
Requires-Dist: tpblite (>=0.8.0,<0.9.0)
Requires-Dist: traitlets (<5.0.0)
Project-URL: Repository, https://github.com/loiccoyle/rofi-tpb
